gqylpy_log/__init__.py
gqylpy_log/g log.py
gqylpy_log-2.0.2.dist-info/LICENSE
gqylpy_log-2.0.2.dist-info/METADATA
gqylpy_log-2.0.2.dist-info/WHEEL
gqylpy_log-2.0.2.dist-info/top_level.txt
gqylpy_log-2.0.2.dist-info/RECORD
