Metadata-Version: 2.1
Name: gqylpy_log
Version: 2.0.2
Summary: Secondary encapsulation `logging`, more convenient and fast to create the logger. Use this module can quickly create instances of `logging.Logger` and complete a series of log configuration, make your code cleaner.
Home-page: http://gqylpy.com
Author: 竹永康
Author-email: <gqylpy@outlook.com>
License: Apache 2.0
Project-URL: Source, https://github.com/gqylpy/gqylpy-log
Classifier: Development Status :: 3 - Alpha
Classifier: Intended Audience :: Developers
Classifier: License :: OSI Approved :: Apache Software License
Classifier: Natural Language :: Chinese (Simplified)
Classifier: Natural Language :: English
Classifier: Operating System :: OS Independent
Classifier: Topic :: Software Development :: Libraries :: Python Modules
Classifier: Topic :: Artistic Software
Classifier: Topic :: Internet :: Log Analysis
Classifier: Topic :: Text Processing
Classifier: Programming Language :: Python :: 3.8
Classifier: Programming Language :: Python :: 3.9
Classifier: Programming Language :: Python :: 3.10
Classifier: Programming Language :: Python :: 3.11
Classifier: Programming Language :: Python :: 3.12
Classifier: Programming Language :: Python :: 3.13
Requires-Python: >=3.8
License-File: LICENSE
